EASGen/EASGen.py
EASGen/__init__.py
EASGen-0.1.9.dist-info/LICENSE
EASGen-0.1.9.dist-info/METADATA
EASGen-0.1.9.dist-info/WHEEL
EASGen-0.1.9.dist-info/top_level.txt
EASGen-0.1.9.dist-info/RECORD
