Metadata-Version: 2.1
Name: EASGen
Version: 0.1.9
Summary: A Python library to generate EAS SAME Audio using Raw Data
Home-page: https://github.com/A-c0rN/EASGen
Author: A-c0rN
Author-email: acrn@gwes-eas.network
License: ODbL-1.0
Keywords: audio sound eas alerting emergency-alert-system
Classifier: Development Status :: 5 - Production/Stable
Classifier: License :: Other/Proprietary License
Classifier: Programming Language :: Python
Classifier: Programming Language :: Python :: 3.6
Classifier: Programming Language :: Python :: 3.7
Classifier: Programming Language :: Python :: 3.8
Classifier: Programming Language :: Python :: 3.9
Classifier: Programming Language :: Python :: 3.10
Classifier: Intended Audience :: Developers
Classifier: Operating System :: OS Independent
Classifier: Topic :: Multimedia :: Sound/Audio
Classifier: Topic :: Software Development :: Libraries
Classifier: Topic :: Utilities
License-File: LICENSE
Requires-Dist: EASGen
